fp_adder.sv

module fp_adder (
    input [32-1:0] i_fp1,
    input [32-1:0] i_fp2,
    output [32-1:0] o_fp
);
    logic fp1_sign;
    logic [7:0] fp1_exp;
    logic [22:0] fp1_man;
    logic [22:0] fp1_man_align;

    logic fp2_sign;
    logic [7:0] fp2_exp;
    logic [22:0] fp2_man;
    logic [22:0] fp2_man_align;

    logic fp_sign;
    logic [7:0] fp_exp;
    logic [7:0] tmp_fp_exp;
    logic [8:0] fp_exp_carry;
    logic [22:0] fp_man;
    logic [24:0] fp_man_carry;

    logic is_fp1_infinity;
    logic is_fp2_infinity;
    logic is_fp1_denorm;
    logic is_fp2_denorm;
    logic larger_fp1_exp;

    // component slicing
    always @ (*) begin
        //fp1
        fp1_sign = i_fp1[31];
        fp1_exp = i_fp1[30:23];
        fp1_man = i_fp1[22:0];
        //fp2
        fp2_sign = i_fp2[31];
        fp2_exp = i_fp2[30:23];
        fp2_man = i_fp2[22:0];
    end

    /* check special cases */
    assign is_fp1_infinity = (fp1_exp == 8'b1111_1111) ? 1 : 0;
    assign is_fp2_infinity = (fp2_exp == 8'b1111_1111) ? 1 : 0;
    //assign is_fp1_NaN = (is_fp1_infinity && (fp1_man != 0)) ? 1 : 0;
    //assign is_fp2_NaN = (is_fp2_infinity && (fp2_man != 0)) ? 1 : 0;
    assign is_fp1_denorm = (fp1_exp == 8'b0000_0000) ? 1 : 0;
    assign is_fp2_denorm = (fp2_exp == 8'b0000_0000) ? 1 : 0;
    assign is_fp1_zero = (is_fp1_denorm && (fp1_man == 0)) ? 1 : 0;
    assign is_fp2_zero = (is_fp2_denorm && (fp2_man == 0)) ? 1 : 0;


    /* Add operation */
    always @ (*) begin
        if(is_fp1_infinity || is_fp2_infinity) begin
            fp_sign = 1'b0;
            tmp_fp_exp = 8'b1111_1111;
            fp_man_carry = 0;
        end
        else if(is_fp1_zero || is_fp2_zero) begin
            if(is_fp1_zero && is_fp2_zero) begin
                fp_sign = 1'b0;
                tmp_fp_exp = 8'b0000_0000;
                fp_man_carry = 0;
            end
            else if(is_fp1_zero) begin
                fp_sign = fp2_sign;
                tmp_fp_exp = fp2_exp;
                fp_man_carry = {2'b00, fp2_man};
            end
            else begin
                fp_sign = fp1_sign;
                tmp_fp_exp = fp1_exp;
                fp_man_carry = {2'b00, fp1_man};
            end
        end
        else begin
            if(is_fp1_denorm || is_fp2_denorm) begin
                if(is_fp1_denorm && is_fp2_denorm) begin
                    if(fp1_man >= fp2_man) begin
                        if((fp1_sign == 0) && (fp2_sign == 1)) begin
                            fp_sign = 0;
                            fp_man_carry = {2'b00, fp1_man} - {2'b00, fp2_man};   // fp = (fp1 - fp2)
                        end
                        else if((fp1_sign == 1) && (fp2_sign == 0)) begin
                            fp_sign = 1;
                            fp_man_carry = {2'b00, fp1_man} - {2'b00, fp2_man};   // fp = -(fp1 - fp2)
                        end
                        else begin
                            fp_sign = fp1_sign;
                            fp_man_carry = {2'b00, fp1_man} + {2'b00, fp2_man};   // fp = +-(fp1 + fp2)                   
                        end
                    end
                    /* |fp1| < |fp2| */
                    else begin
                        if((fp1_sign == 0) && (fp2_sign == 1)) begin
                            fp_sign = 1;
                            fp_man_carry = {2'b01, fp2_man} - {2'b01, fp1_man};   // fp = -(fp2 - fp1)
                        end
                        else if((fp1_sign == 1) && (fp2_sign == 0)) begin
                            fp_sign = 0;
                            fp_man_carry = {2'b01, fp2_man} - {2'b01, fp1_man};   // fp = (fp2 - fp1)
                        end
                        else begin
                            fp_sign = fp2_sign;
                            fp_man_carry = {2'b01, fp2_man} + {2'b01, fp1_man};   // fp = +-(fp1 + fp2)                   
                        end
                    end
                end
                /* |fp2| > |fp1|, since fp1 is 0.xxx... */
                else if(is_fp1_denorm) begin
                    tmp_fp_exp = fp2_exp;                                       // set exponent
                    fp1_man_align = {1'b0, fp1_man[22:1]} >> (fp2_exp - 1);           // mantissa alignment
                    /* fp1 + (-fp2) */
                    if((fp1_sign == 0) && (fp2_sign == 1)) begin
                        fp_sign = 1;
                        fp_man_carry = {2'b01, fp2_man} - {2'b00, fp1_man_align};   // fp = -(fp2 - fp1)
                    end
                    /* (-fp1) + fp2 */
                    else if((fp1_sign == 1) && (fp2_sign == 0)) begin
                        fp_sign = 0;
                        fp_man_carry = {2'b01, fp2_man} - {2'b00, fp1_man_align};   // fp = (fp2 - fp1)
                    end
                    /* (-fp1) + (-fp2) or fp1 + fp2 */
                    else begin
                        fp_sign = fp1_sign;
                        fp_man_carry = {2'b01, fp2_man} + {2'b00, fp1_man_align};   // fp = +-(fp2 + fp1)
                    end
                end
                /* |fp1| > |fp2|, since fp2 is 0.xxx... */
                else begin               
                    tmp_fp_exp = fp1_exp;                                       // set exponent
                    fp2_man_align = {1'b0, fp2_man[22:1]} >> (fp1_exp - 1);           // mantissa alignment 
                    /* fp1 + (-fp2) */
                    if((fp1_sign == 0) && (fp2_sign == 1)) begin
                        fp_sign = 0;
                        fp_man_carry = {2'b01, fp1_man} - {2'b00, fp2_man_align};   // fp = fp1 - fp2
                    end
                    /* (-fp1) + fp2 */
                    else if((fp1_sign == 1) && (fp2_sign == 0)) begin               
                        fp_sign = 1;
                        fp_man_carry = {2'b01, fp1_man} - {2'b00, fp2_man_align};   // fp = -(fp1 - fp2) 
                    end
                    /* (-fp1) + (-fp2) or fp1 + fp2 */
                    else begin
                        fp_sign = fp2_sign;
                        fp_man_carry = {2'b01, fp1_man} + {2'b00, fp2_man_align};   // fp = +-(fp1 + fp2)
                    end
                end
            end
            /* two normalized number */
            else begin
                if(fp1_exp == fp2_exp) begin
                    tmp_fp_exp = fp1_exp;                                           // set exponent
                    /* |fp1| >= |fp2| */
                    if(fp1_man >= fp2_man) begin
                        if((fp1_sign == 0) && (fp2_sign == 1)) begin
                            fp_sign = 0;
                            fp_man_carry = {2'b01, fp1_man} - {2'b01, fp2_man};   // fp = (fp1 - fp2)
                        end
                        else if((fp1_sign == 1) && (fp2_sign == 0)) begin
                            fp_sign = 1;
                            fp_man_carry = {2'b01, fp1_man} - {2'b01, fp2_man};   // fp = -(fp1 - fp2)
                        end
                        else begin
                            fp_sign = fp1_sign;
                            fp_man_carry = {2'b01, fp1_man} + {2'b01, fp2_man};   // fp = +-(fp1 + fp2)                   
                        end
                    end
                    /* |fp1| < |fp2| */
                    else begin
                        if((fp1_sign == 0) && (fp2_sign == 1)) begin
                            fp_sign = 1;
                            fp_man_carry = {2'b01, fp2_man} - {2'b01, fp1_man};   // fp = -(fp2 - fp1)
                        end
                        else if((fp1_sign == 1) && (fp2_sign == 0)) begin
                            fp_sign = 0;
                            fp_man_carry = {2'b01, fp2_man} - {2'b01, fp1_man};   // fp = (fp2 - fp1)
                        end
                        else begin
                            fp_sign = fp2_sign;
                            fp_man_carry = {2'b01, fp2_man} + {2'b01, fp1_man};   // fp = +-(fp1 + fp2)                   
                        end
                    end
                end
                /* |fp2| > |fp1| */
                else if(fp2_exp > fp1_exp) begin
                    tmp_fp_exp = fp2_exp;                                           // set exponent 
                    fp1_man_align = {1'b1, fp1_man[22:1]} >> (fp2_exp - fp1_exp - 1);     // mantissa align
                    /* fp1 + (-fp2) */
                    if((fp1_sign == 0) && (fp2_sign == 1)) begin
                        fp_sign = 1;
                        fp_man_carry = {2'b01, fp2_man} - {2'b00, fp1_man_align};   // fp = -(fp2 - fp1)
                    end
                    /* (-fp1) + fp2 */
                    else if((fp1_sign == 1) && (fp2_sign == 0)) begin            
                        fp_sign = 0;    
                        fp_man_carry = {2'b01, fp2_man} - {2'b00, fp1_man_align};   // fp = (fp2 - fp1)
                    end
                    /* (-fp1) + (-fp2) or fp1 + fp2 */
                    else begin
                        fp_sign = fp1_sign;
                        fp_man_carry = {2'b01, fp2_man} + {2'b00, fp1_man_align};   // fp = +-(fp2 + fp1)
                    end
                end
                /* |fp2| < |fp1| */
                else begin
                    tmp_fp_exp = fp1_exp;                                           // set exponent 
                    fp2_man_align = {1'b1, fp2_man[22:1]} >> (fp1_exp - fp2_exp - 1);     // mantissa alignment 
                    /* fp1 + (-fp2) */
                    if((fp1_sign == 0) && (fp2_sign == 1)) begin
                        fp_sign = 0;
                        fp_man_carry = {2'b01, fp1_man} - {2'b00, fp2_man_align};   // fp = (fp1 - fp2)
                    end
                    /* (-fp1) + fp2 */
                    else if((fp1_sign == 1) && (fp2_sign == 0)) begin
                        fp_sign = 1;
                        fp_man_carry = {2'b01, fp1_man} - {2'b00, fp2_man_align};   // fp = -(fp1 - fp2)
                    end
                    /* (-fp1) + (-fp2) or fp1 + fp2 */
                    else begin
                        fp_sign = fp2_sign;
                        fp_man_carry = {2'b01, fp1_man} + {2'b00, fp2_man_align};   // fp = +-(fp1 + fp2)
                    end
                end
            end
        end
    end


    /* making implicit leading 1 and check for exponent overflow and underflow */
    always @ (*) begin
        if(fp_man_carry[24] == 1'b1) begin
            if((tmp_fp_exp + 1) > 8'b1111_1110) begin
                fp_exp = 8'b1111_1111;
                fp_man = 0;
            end
            else begin
                fp_exp = tmp_fp_exp + 1;
                fp_man = fp_man_carry[23:1];
            end
        end
        else if(fp_man_carry[23] == 1'b1) begin
            fp_exp = tmp_fp_exp;
            fp_man = fp_man_carry[22:0];
        end
        else if(fp_man_carry[22] == 1'b1) begin
            if(({1'b1, tmp_fp_exp} - 1) < 9'b1_0000_0000) begin
                fp_exp = 8'b0000_0000;
                fp_man = fp_man_carry[22:0] << tmp_fp_exp;
            end
            else begin
                fp_exp = tmp_fp_exp - 1;
                fp_man = fp_man_carry[22:0] << 1;
            end 
        end
        else if(fp_man_carry[21] == 1'b1) begin
            if(({1'b1, tmp_fp_exp} - 2) < 9'b1_0000_0000) begin
                fp_exp = 8'b0000_0000;
                fp_man = fp_man_carry[22:0] << tmp_fp_exp;
            end
            else begin
                fp_exp = tmp_fp_exp - 2;
                fp_man = fp_man_carry[22:0] << 2;
            end 
        end
        else if(fp_man_carry[20] == 1'b1) begin
            if(({1'b1, tmp_fp_exp} - 3) < 9'b1_0000_0000) begin
                fp_exp = 8'b0000_0000;
                fp_man = fp_man_carry[22:0] << tmp_fp_exp;
            end
            else begin
                fp_exp = tmp_fp_exp - 3;
                fp_man = fp_man_carry[22:0] << 3;
            end 
        end
        else if(fp_man_carry[19] == 1'b1) begin
            if(({1'b1, tmp_fp_exp} - 4) < 9'b1_0000_0000) begin
                fp_exp = 8'b0000_0000;
                fp_man = fp_man_carry[22:0] << tmp_fp_exp;
            end
            else begin
                fp_exp = tmp_fp_exp - 4;
                fp_man = fp_man_carry[22:0] << 4;
            end 
        end
        else if(fp_man_carry[18] == 1'b1) begin
            if(({1'b1, tmp_fp_exp} - 5) < 9'b1_0000_0000) begin
                fp_exp = 8'b0000_0000;
                fp_man = fp_man_carry[22:0] << tmp_fp_exp;
            end
            else begin
                fp_exp = tmp_fp_exp - 5;
                fp_man = fp_man_carry[22:0] << 5;
            end 
        end
        else if(fp_man_carry[17] == 1'b1) begin
            if(({1'b1, tmp_fp_exp} - 6) < 9'b1_0000_0000) begin
                fp_exp = 8'b0000_0000;
                fp_man = fp_man_carry[22:0] << tmp_fp_exp;
            end
            else begin
                fp_exp = tmp_fp_exp - 6;
                fp_man = fp_man_carry[22:0] << 6;
            end 
        end
        else if(fp_man_carry[16] == 1'b1) begin
            if(({1'b1, tmp_fp_exp} - 7) < 9'b1_0000_0000) begin
                fp_exp = 8'b0000_0000;
                fp_man = fp_man_carry[22:0] << tmp_fp_exp;
            end
            else begin
                fp_exp = tmp_fp_exp - 7;
                fp_man = fp_man_carry[22:0] << 7;
            end 
        end
        else if(fp_man_carry[15] == 1'b1) begin
            if(({1'b1, tmp_fp_exp} - 8) < 9'b1_0000_0000) begin
                fp_exp = 8'b0000_0000;
                fp_man = fp_man_carry[22:0] << tmp_fp_exp;
            end
            else begin
                fp_exp = tmp_fp_exp - 8;
                fp_man = fp_man_carry[22:0] << 8;
            end 
        end
        else if(fp_man_carry[14] == 1'b1) begin
            if(({1'b1, tmp_fp_exp} - 9) < 9'b1_0000_0000) begin
                fp_exp = 8'b0000_0000;
                fp_man = fp_man_carry[22:0] << tmp_fp_exp;
            end
            else begin
                fp_exp = tmp_fp_exp - 9;
                fp_man = fp_man_carry[22:0] << 9;
            end 
        end
        else if(fp_man_carry[13] == 1'b1) begin
            if(({1'b1, tmp_fp_exp} - 10) < 9'b1_0000_0000) begin
                fp_exp = 8'b0000_0000;
                fp_man = fp_man_carry[22:0] << tmp_fp_exp;
            end
            else begin
                fp_exp = tmp_fp_exp - 10;
                fp_man = fp_man_carry[22:0] << 10;
            end 
        end
        else if(fp_man_carry[12] == 1'b1) begin
            if(({1'b1, tmp_fp_exp} - 11) < 9'b1_0000_0000) begin
                fp_exp = 8'b0000_0000;
                fp_man = fp_man_carry[22:0] << tmp_fp_exp;
            end
            else begin
                fp_exp = tmp_fp_exp - 11;
                fp_man = fp_man_carry[22:0] << 11;
            end 
        end
        else if(fp_man_carry[11] == 1'b1) begin
            if(({1'b1, tmp_fp_exp} - 12) < 9'b1_0000_0000) begin
                fp_exp = 8'b0000_0000;
                fp_man = fp_man_carry[22:0] << tmp_fp_exp;
            end
            else begin
                fp_exp = tmp_fp_exp - 12;
                fp_man = fp_man_carry[22:0] << 12;
            end 
        end
        else if(fp_man_carry[10] == 1'b1) begin
            if(({1'b1, tmp_fp_exp} - 13) < 9'b1_0000_0000) begin
                fp_exp = 8'b0000_0000;
                fp_man = fp_man_carry[22:0] << tmp_fp_exp;
            end
            else begin
                fp_exp = tmp_fp_exp - 13;
                fp_man = fp_man_carry[22:0] << 13;
            end 
        end
        else if(fp_man_carry[9] == 1'b1) begin
            if(({1'b1, tmp_fp_exp} - 14) < 9'b1_0000_0000) begin
                fp_exp = 8'b0000_0000;
                fp_man = fp_man_carry[22:0] << tmp_fp_exp;
            end
            else begin
                fp_exp = tmp_fp_exp - 14;
                fp_man = fp_man_carry[22:0] << 14;
            end 
        end
        else if(fp_man_carry[8] == 1'b1) begin
            if(({1'b1, tmp_fp_exp} - 15) < 9'b1_0000_0000) begin
                fp_exp = 8'b0000_0000;
                fp_man = fp_man_carry[22:0] << tmp_fp_exp;
            end
            else begin
                fp_exp = tmp_fp_exp - 15;
                fp_man = fp_man_carry[22:0] << 15;
            end 
        end
        else if(fp_man_carry[7] == 1'b1) begin
            if(({1'b1, tmp_fp_exp} - 16) < 9'b1_0000_0000) begin
                fp_exp = 8'b0000_0000;
                fp_man = fp_man_carry[22:0] << tmp_fp_exp;
            end
            else begin
                fp_exp = tmp_fp_exp - 16;
                fp_man = fp_man_carry[22:0] << 16;
            end 
        end
        else if(fp_man_carry[6] == 1'b1) begin
            if(({1'b1, tmp_fp_exp} - 17) < 9'b1_0000_0000) begin
                fp_exp = 8'b0000_0000;
                fp_man = fp_man_carry[22:0] << tmp_fp_exp;
            end
            else begin
                fp_exp = tmp_fp_exp - 17;
                fp_man = fp_man_carry[22:0] << 17;
            end 
        end
        else if(fp_man_carry[5] == 1'b1) begin
            if(({1'b1, tmp_fp_exp} - 18) < 9'b1_0000_0000) begin
                fp_exp = 8'b0000_0000;
                fp_man = fp_man_carry[22:0] << tmp_fp_exp;
            end
            else begin
                fp_exp = tmp_fp_exp - 18;
                fp_man = fp_man_carry[22:0] << 18;
            end 
        end
        else if(fp_man_carry[4] == 1'b1) begin
            if(({1'b1, tmp_fp_exp} - 19) < 9'b1_0000_0000) begin
                fp_exp = 8'b0000_0000;
                fp_man = fp_man_carry[22:0] << tmp_fp_exp;
            end
            else begin
                fp_exp = tmp_fp_exp - 19;
                fp_man = fp_man_carry[22:0] << 19;
            end 
        end
        else if(fp_man_carry[3] == 1'b1) begin
            if(({1'b1, tmp_fp_exp} - 20) < 9'b1_0000_0000) begin
                fp_exp = 8'b0000_0000;
                fp_man = fp_man_carry[22:0] << tmp_fp_exp;
            end
            else begin
                fp_exp = tmp_fp_exp - 20;
                fp_man = fp_man_carry[22:0] << 20;
            end 
        end
        else if(fp_man_carry[2] == 1'b1) begin
            if(({1'b1, tmp_fp_exp} - 21) < 9'b1_0000_0000) begin
                fp_exp = 8'b0000_0000;
                fp_man = fp_man_carry[22:0] << tmp_fp_exp;
            end
            else begin
                fp_exp = tmp_fp_exp - 21;
                fp_man = fp_man_carry[22:0] << 21;
            end 
        end
        else if(fp_man_carry[1] == 1'b1) begin
            if(({1'b1, tmp_fp_exp} - 22) < 9'b1_0000_0000) begin
                fp_exp = 8'b0000_0000;
                fp_man = fp_man_carry[22:0] << tmp_fp_exp;
            end
            else begin
                fp_exp = tmp_fp_exp - 22;
                fp_man = fp_man_carry[22:0] << 22;
            end 
        end
        else if(fp_man_carry[0] == 1'b1) begin
            if(({1'b1, tmp_fp_exp} - 23) < 9'b1_0000_0000) begin
                fp_exp = 8'b0000_0000;
                fp_man = fp_man_carry[22:0] << tmp_fp_exp;
            end
            else begin
                fp_exp = tmp_fp_exp - 23;
                fp_man = fp_man_carry[22:0] << 23;
            end 
        end
        else begin
            fp_exp = 8'b0000_0000;
            fp_man = 0;
        end
    end

    assign o_fp = {fp_sign, fp_exp, fp_man};

endmodule

tb_fp_adder.sv
module testbench;

logic clk, reset;

logic [31:0] fp1;
logic [31:0] fp2;
logic [31:0] out;

logic [31:0] expected;

logic [32-1:0] vectornum, errors;
logic [(32+32+32)-1:0] testvectors_fps [0:10000];

fp_adder /* #( ) */ dut(
  .i_fp1(fp1),
  .i_fp2(fp2),
  .o_fp(out)
);

always #5 clk = ~clk;




initial begin
  $readmemb("./fps.tv", testvectors_fps);
  vectornum = 0; errors = 0;

  $dumpfile("testbench.vcd");
	$dumpvars(0, testbench);
  clk = 0;
  reset = 1; #27; reset = 0;
end

always @ (posedge clk) begin
  #1; {fp1, fp2, expected} = testvectors_fps[vectornum];
end


always @ (negedge clk) begin
  if(~reset) begin
    if(out[31:2] !== expected[31:2]) begin
      $display("Error: inputs fp1 = %b, fp2 = %b",fp1, fp2);
      $display(" outputs = %h (%h expected)", out, expected);
      errors = errors + 1;
    end
    //else begin
    //  $display("success: inputs fp1 = %b, fp2 = %b",fp1, fp2);
    //  $display(" outputs = %b (%b expected)", out, expected);
    //end
  end
end

always @(negedge clk) begin
  if (~reset) begin

    vectornum = vectornum + 1;

    if (testvectors_fps[vectornum] === 96'bx) begin
      $display("%d tests completed with %d errors", vectornum, errors);
      $finish;
    end
  end
end

endmodule

testbench.vcd
$date
	Sun Aug 13 21:35:29 2023
$end
$version
	Icarus Verilog
$end
$timescale
	1s
$end
$scope module testbench $end
$var wire 32 ! out [31:0] $end
$var reg 1 " clk $end
$var reg 32 # errors [31:0] $end
$var reg 32 $ expected [31:0] $end
$var reg 32 % fp1 [31:0] $end
$var reg 32 & fp2 [31:0] $end
$var reg 1 ' reset $end
$var reg 32 ( vectornum [31:0] $end
$scope module dut $end
$var wire 32 ) i_fp1 [31:0] $end
$var wire 32 * i_fp2 [31:0] $end
$var wire 32 + o_fp [31:0] $end
$var wire 1 , is_fp2_zero $end
$var wire 1 - is_fp2_infinity $end
$var wire 1 . is_fp2_denorm $end
$var wire 1 / is_fp1_zero $end
$var wire 1 0 is_fp1_infinity $end
$var wire 1 1 is_fp1_denorm $end
$var reg 8 2 fp1_exp [7:0] $end
$var reg 23 3 fp1_man [22:0] $end
$var reg 23 4 fp1_man_align [22:0] $end
$var reg 1 5 fp1_sign $end
$var reg 8 6 fp2_exp [7:0] $end
$var reg 23 7 fp2_man [22:0] $end
$var reg 23 8 fp2_man_align [22:0] $end
$var reg 1 9 fp2_sign $end
$var reg 8 : fp_exp [7:0] $end
$var reg 23 ; fp_man [22:0] $end
$var reg 25 < fp_man_carry [24:0] $end
$var reg 1 = fp_sign $end
$var reg 8 > tmp_fp_exp [7:0] $end
$upscope $end
$upscope $end
$enddefinitions $end
#0
$dumpvars
bx >
x=
bx <
bx ;
bx :
x9
bx 8
bx 7
bx 6
x5
bx 4
bx 3
bx 2
x1
x0
x/
x.
x-
x,
bx +
bx *
bx )
b0 (
1'
bx &
bx %
bx $
b0 #
0"
bx !
$end
#5
1"
#6
0,
0/
0-
0.
00
11
b1111110110010000000 ;
b111 :
b100001111110110010000000 <
b11100001111110110010000000 !
b11100001111110110010000000 +
0=
b1101111110110110 4
b111 >
b1110000110011001010 7
b111 6
09
b11011111101101101010000 3
b0 2
05
b11011111101101101010000 %
b11011111101101101010000 )
b11100001110000110011001010 &
b11100001110000110011001010 *
b11100010001100110000110111 $
#10
0"
#15
1"
#20
0"
#25
1"
#27
0'
#30
b1 #
b1 (
0"
#35
1"
#36
01
b1110001000001101011000 ;
b101110001000001101011000 <
b10000011101110001000001101011000 !
b10000011101110001000001101011000 +
1=
b1101110011101110011001 4
b10100011110111111 7
19
b10111001110111001100110 3
b101 2
15
b10000010110111001110111001100110 %
b10000010110111001110111001100110 )
b10000011100000010100011110111111 &
b10000011100000010100011110111111 *
b10000011101110001000001101011000 $
#40
b10 (
0"
#45
1"
#46
b10100001010111001001110 ;
b10000010010100001010111001001110 !
b10000010010100001010111001001110 +
b100 :
b11010000101011100100111 <
b11111111110111101001110 4
b101 >
b11010000100011001110101 7
b101 6
b11111111101111010011101 3
b100 2
05
b10011111111101111010011101 %
b10011111111101111010011101 )
b10000010111010000100011001110101 &
b10000010111010000100011001110101 *
b10000010010100001010111001001101 $
#50
b11 (
0"
#55
1"
#56
b1000100101110111010001 ;
b10000001101000100101110111010001 !
b10000001101000100101110111010001 +
b11 :
b1010001001011101110100011 <
b11011000000001000000011 8
b10 >
b10110000000010000000110 7
b1 6
b10110001011100110100000 3
b10 2
15
b10000001010110001011100110100000 %
b10000001010110001011100110100000 )
b10000000110110000000010000000110 &
b10000000110110000000010000000110 *
b10000001101000100101110111010010 $
#60
b100 (
0"
#65
1"
#66
b10111111011010010 ;
b111 :
b1000000101111110110100101 <
b11100000010111111011010010 !
b11100000010111111011010010 +
0=
b1000111011000011101 4
b110 >
b11111101000011110001000 7
b110 6
09
b11101100001110101000 3
b1 2
05
b100011101100001110101000 %
b100011101100001110101000 )
b11011111101000011110001000 &
b11011111101000011110001000 *
b11100000010111111011010011 $
#70
b101 (
0"
#75
1"
#76
b1011001100001001111111 ;
b110 :
b101011001100001001111111 <
b10000011001011001100001001111111 !
b10000011001011001100001001111111 +
1=
b1000100010101111000 4
b1100010000011111110111 7
19
b10001010111100011100 3
b100010001010111100011100 %
b100010001010111100011100 )
b10000011001100010000011111110111 &
b10000011001100010000011111110111 *
b10000011001011001100001001111110 $
#80
b110 (
0"
#85
1"
#86
1.
b10000101011101111110 ;
b10 :
b1000100001010111011111101 <
b1000010000101011101111110 !
b1000010000101011101111110 +
0=
b101010111111101001010 8
b1 >
b1010101111111010010101 7
b0 6
09
b11110110010111110110011 3
b111110110010111110110011 %
b111110110010111110110011 )
b1010101111111010010101 &
b1010101111111010010101 *
b1000100110001011100100100 $
#90
b10 #
b111 (
0"
#95
1"
#96
b1001101100110110111111 4
0.
b10011100000111111110000 ;
b110011100000111111110000 !
b110011100000111111110000 +
b1 :
11
b110011100000111111110000 <
b0 8
b1 >
b1001110100001000110001 7
b1 6
b10011011001101101111111 3
b0 2
b10011011001101101111111 %
b10011011001101101111111 )
b101001110100001000110001 &
b101001110100001000110001 *
b111101001101110110110000 $
#100
b1000 (
b11 #
0"
#105
1"
#106
01
b10011001101000000110100 ;
b1010011001101000000110100 !
b1010011001101000000110100 +
b10 :
b11001100110100000011010 <
b11000101010010101101100 4
b11 >
b10010010000110110000110 7
b11 6
b10001010100101011011000 3
b10 2
15
b10000001010001010100101011011000 %
b10000001010001010100101011011000 )
b1110010010000110110000110 &
b1110010010000110110000110 *
b1010011001101000000110100 $
#110
b1001 (
0"
#115
1"
#116
b1000111000001010110000 ;
b100001000111000001010110000 !
b100001000111000001010110000 +
b1000 :
b1010001110000010101100000 <
b111 >
b10001011111001101100111 7
b111 6
b10001000111111001 3
b111 2
05
b11100000010001000111111001 %
b11100000010001000111111001 )
b11110001011111001101100111 &
b11110001011111001101100111 *
b100001000111000001010110000 $
#120
b1010 (
0"
#125
1"
#126
b11011100000010011100 ;
b110 :
b1000110111000000100111001 <
b10000011000011011100000010011100 !
b10000011000011011100000010011100 +
1=
b10111110001000010110111 4
b101 >
b1111000111000010000010 7
b101 6
19
b1111100010000101101111 3
b100 2
15
b10000010001111100010000101101111 %
b10000010001111100010000101101111 )
b10000010101111000111000010000010 &
b10000010101111000111000010000010 *
b10000011000011011100000010011101 $
#130
b1011 (
0"
#135
1"
#136
b1101000111100001010111 ;
b111 :
b101101000111100001010111 <
b11101101000111100001010111 !
b11101101000111100001010111 +
0=
b101010000100111010 4
b111 >
b1100011101011100011101 7
b111 6
09
b1010000100111010001010 3
b1 2
05
b101010000100111010001010 %
b101010000100111010001010 )
b11101100011101011100011101 &
b11101100011101011100011101 *
b11101101000111100001010111 $
#140
b1100 (
0"
#145
1"
#146
b1010001010010011100010 ;
b10101010001010010011100010 !
b10101010001010010011100010 +
b101 :
b101010001010010011100010 <
b11010010010010001001 8
b101 >
b10100100100100010010100 7
b1 6
b110111000000001011001 3
b101 2
b10100110111000000001011001 %
b10100110111000000001011001 )
b110100100100100010010100 &
b110100100100100010010100 *
b10101010001010010011100010 $
#150
b1101 (
0"
#155
1"
#156
b10011011111001110110000 ;
b10 :
b11001101111100111011 <
b10000001010011011111001110110000 !
b10000001010011011111001110110000 +
1=
b110 >
b1100100010001010101001 7
b110 6
19
b1001010100001101101110 3
b110 2
b11001001010100001101101110 %
b11001001010100001101101110 )
b10000011001100100010001010101001 &
b10000011001100100010001010101001 *
b10000001010011011111001110110000 $
#160
b1110 (
0"
#165
1"
#166
b11000101000010111111 ;
b110 :
b1000110001010000101111111 <
b11000011000101000010111111 !
b11000011000101000010111111 +
0=
b1010010110111100000111 4
b101 >
b11011110011001001111000 7
b101 6
09
b1001011011110000011101 3
b11 2
b1101001011011110000011101 %
b1101001011011110000011101 )
b10111011110011001001111000 &
b10111011110011001001111000 *
b11000011000101000011000000 $
#170
b100 #
b1111 (
0"
#175
1"
#176
b1101000000111100100000 ;
b11101101000000111100100000 !
b11101101000000111100100000 +
b111 :
b101101000000111100100000 <
b101001111111010011110 4
b111 >
b10010010000110110111110 7
b111 6
b1001111111010011110101 3
b100 2
15
b10000010001001111111010011110101 %
b10000010001001111111010011110101 )
b11110010010000110110111110 &
b11110010010000110110111110 *
b11101101000000111100011111 $
#180
b10000 (
b101 #
0"
#185
1"
#186
b1101111110011010000 ;
b1100001101111110011010000 !
b1100001101111110011010000 +
b11 :
b100001101111110011010000 <
b1100000110000001001011 8
b11 >
b10000011000000100101100 7
b1 6
19
b1101110101110100011011 3
b11 2
05
b1101101110101110100011011 %
b1101101110101110100011011 )
b10000000110000011000000100101100 &
b10000000110000011000000100101100 *
b1100001101111110011010000 $
#190
b10001 (
0"
#195
1"
#196
1.
b10111000101101111110010 ;
b11010111000101101111110010 !
b11010111000101101111110010 +
b110 :
b110111000101101111110010 <
b11011001110101111 8
b110 >
b11011001110101111111010 7
b0 6
09
b10110101010100001000011 3
b110 2
b11010110101010100001000011 %
b11010110101010100001000011 )
b11011001110101111111010 &
b11011001110101111111010 *
b11010111100000111110100011 $
#200
b10010 (
b110 #
0"
#205
1"
#206
0.
b10101100011000011011010 ;
b10 :
b1101011000110000110110101 <
b10000001010101100011000011011010 !
b10000001010101100011000011011010 +
1=
b110100000100111010000 8
b1 >
b1101000001001110100000 7
b1 6
19
b11110000100111000010101 3
b1 2
15
b10000000111110000100111000010101 %
b10000000111110000100111000010101 )
b10000000101101000001001110100000 &
b10000000101101000001001110100000 *
b10000001010101100011000011011010 $
#210
b10011 (
0"
#215
1"
#216
b10000001011110111111010 ;
b100 :
11
b110000001011110111111010 <
b10010000001011110111111010 !
b10010000001011110111111010 +
0=
b111100010101101010 4
b100 >
b10001001000001101100100 7
b100 6
09
b1111000101011010100110 3
b0 2
b10000000001111000101011010100110 %
b10000000001111000101011010100110 )
b10010001001000001101100100 &
b10010001001000001101100100 *
b10001111001111100010001111 $
#220
b10100 (
b111 #
0"
#225
1"
#226
b111 :
b1110101111011011100000 8
b110 >
b101100000001000111101 ;
01
b1001011000000010001111010 <
b10000011100101100000001000111101 !
b10000011100101100000001000111101 +
1=
b1110001000011011001 4
b11010111101101110000001 7
19
b11100010000110110011010 3
b110 2
b10000011011100010000110110011010 %
b10000011011100010000110110011010 )
b10000010011010111101101110000001 &
b10000010011010111101101110000001 *
b10000011100101100000001000111101 $
#230
b10101 (
0"
#235
1"
#236
b10000011100110001111111110000101 !
b10000011100110001111111110000101 +
b110001111111110000101 ;
b100110001111111110000101 <
b1011000011011000010 4
b111 >
b111101000011001000111 7
b111 6
b1100001101100001010111 3
b10 2
05
b1001100001101100001010111 %
b1001100001101100001010111 )
b10000011100111101000011001000111 &
b10000011100111101000011001000111 *
b10000011100110001111111110000100 $
#240
b10110 (
0"
#245
1"
#246
1.
b1100110100001110001110 ;
b10 :
b101100110100001110001110 <
b1001100110100001110001110 !
b1001100110100001110001110 +
0=
b111100101101110000111 8
b10 >
b11110010110111000011100 7
b0 6
b10100011001111100010101 3
b1010100011001111100010101 %
b1010100011001111100010101 )
b10000000011110010110111000011100 &
b10000000011110010110111000011100 *
b1000101001110100000000111 $
#250
b1000 #
b10111 (
0"
#255
1"
#256
0.
b1000110000110000000010 ;
b10101000110000110000000010 !
b10101000110000110000000010 +
b101 :
b10100011000011000000001 <
b11100110110100000011101 8
b110 >
b11001101101000000111010 7
b101 6
b10001001110111000011110 3
b110 2
b11010001001110111000011110 %
b11010001001110111000011110 )
b10000010111001101101000000111010 &
b10000010111001101101000000111010 *
b10101000110000110000000010 $
#260
b11000 (
0"
#265
1"
